LICENSE
README.md
setup.py
boon/__init__.py
boon/db/__init__.py
boon/db/database.py
boon/db/database_execute.py
boon/db/local_cache.py
boon/db/mysql.py
boon/db/redis.py
boon/db/sqlite3.py
boon/protocol/__init__.py
boon/protocol/context.py
boon/protocol/http_headers.py
boon/protocol/response_json.py
boon/utils/__init__.py
boon/utils/conf.py
boon/utils/data.py
boon/utils/http.py
boon/utils/log.py
boon_common.egg-info/PKG-INFO
boon_common.egg-info/SOURCES.txt
boon_common.egg-info/dependency_links.txt
boon_common.egg-info/requires.txt
boon_common.egg-info/top_level.txt